README.txt
setup.py
collective/__init__.py
collective.slideshowfolder.egg-info/PKG-INFO
collective.slideshowfolder.egg-info/SOURCES.txt
collective.slideshowfolder.egg-info/dependency_links.txt
collective.slideshowfolder.egg-info/entry_points.txt
collective.slideshowfolder.egg-info/namespace_packages.txt
collective.slideshowfolder.egg-info/not-zip-safe
collective.slideshowfolder.egg-info/requires.txt
collective.slideshowfolder.egg-info/top_level.txt
collective/slideshowfolder/README.txt
collective/slideshowfolder/__init__.py
collective/slideshowfolder/browser.py
collective/slideshowfolder/configure.zcml
collective/slideshowfolder/content.py
collective/slideshowfolder/event.py
collective/slideshowfolder/field.py
collective/slideshowfolder/overrides.zcml
collective/slideshowfolder/portlets.txt
collective/slideshowfolder/testing.py
collective/slideshowfolder/tests.py
collective/slideshowfolder/portlets/__init__.py
collective/slideshowfolder/portlets/assignment.py
collective/slideshowfolder/portlets/browser.py
collective/slideshowfolder/portlets/configure.zcml
collective/slideshowfolder/portlets/renderer.py
collective/slideshowfolder/portlets/slideshow.pt
collective/slideshowfolder/profiles/default/factorytool.xml
collective/slideshowfolder/profiles/default/jsregistry.xml
collective/slideshowfolder/profiles/default/metadata.xml
collective/slideshowfolder/profiles/default/portlets.xml
collective/slideshowfolder/profiles/default/skins.xml
collective/slideshowfolder/profiles/default/types.xml
collective/slideshowfolder/profiles/default/types/SlideshowImage.xml
collective/slideshowfolder/skins/collective_slideshowfolder/slideshow_settings.js.pt
docs/HISTORY.txt
docs/TODO.txt