Metadata-Version: 1.0
Name: collective.slideshowfolder
Version: 0.7
Summary: Somtimes useful extensions to Products.slideshowfolder
Home-page: http://pypi.python.org/pypi/collective.slideshowfolder
Author: Ross Patterson
Author-email: me@rpatterson.net
License: GPL
Platform: UNKNOWN
Classifier: Programming Language :: Python
Classifier: Topic :: Software Development :: Libraries :: Python Modules
